academic_ads_bibtex/__init__.py
academic_ads_bibtex/converter.py
academic_ads_bibtex/logger.py
academic_ads_bibtex/database/bibtex_journals.db
academic_ads_bibtex-0.2.3.data/scripts/academic_ads_bibtex
academic_ads_bibtex-0.2.3.dist-info/LICENSE
academic_ads_bibtex-0.2.3.dist-info/METADATA
academic_ads_bibtex-0.2.3.dist-info/WHEEL
academic_ads_bibtex-0.2.3.dist-info/top_level.txt
academic_ads_bibtex-0.2.3.dist-info/RECORD
