Metadata-Version: 2.1
Name: academic-ads-bibtex
Version: 0.2.3
Summary: Construct a proper BibTeX file to use with the Hugo Academic theme from ADS export
Home-page: https://github.com/astrochun/academic-ads-bibtex
Author: Chun Ly
Author-email: astro.chun@gmail.com
License: GNU GPLv3
Platform: UNKNOWN
Classifier: Development Status :: 4 - Beta
Classifier: Programming Language :: Python :: 3 :: Only
Classifier: Programming Language :: Python :: 3.7
Classifier: Programming Language :: Python :: 3.8
Classifier: Programming Language :: Python :: 3.9
Requires-Python: >=3.7
